{
    "20th": [
        {
            "algorithm": "ga",
            "fitness": 98.1712,
            "polygons": 289,
            "target_img_size": 97035,
            "generated_img_size": 175727
        },
        {
            "algorithm": "hcfi",
            "fitness": 98.8762,
            "polygons": 104,
            "target_img_size": 97035,
            "generated_img_size": 90690
        },
        {
            "algorithm": "hcbi",
            "fitness": 98.73140000000001,
            "polygons": 114,
            "target_img_size": 97035,
            "generated_img_size": 92355
        },
        {
            "algorithm": "sa",
            "fitness": 98.9134,
            "polygons": 118,
            "target_img_size": 97035,
            "generated_img_size": 98267
        }
    ],
    "86": [
        {
            "algorithm": "ga",
            "fitness": 97.3925,
            "polygons": 287,
            "target_img_size": 880182,
            "generated_img_size": 181390
        },
        {
            "algorithm": "hcfi",
            "fitness": 98.32260000000001,
            "polygons": 76,
            "target_img_size": 880182,
            "generated_img_size": 78067
        },
        {
            "algorithm": "hcbi",
            "fitness": 98.4112,
            "polygons": 86,
            "target_img_size": 880182,
            "generated_img_size": 83058
        },
        {
            "algorithm": "sa",
            "fitness": 98.4106,
            "polygons": 185,
            "target_img_size": 880182,
            "generated_img_size": 132188
        }
    ],
    "bowl": [
        {
            "algorithm": "ga",
            "fitness": 99.3291,
            "polygons": 70,
            "target_img_size": 119571,
            "generated_img_size": 71769
        },
        {
            "algorithm": "hcfi",
            "fitness": 99.5452,
            "polygons": 88,
            "target_img_size": 119571,
            "generated_img_size": 81402
        },
        {
            "algorithm": "hcbi",
            "fitness": 99.5753,
            "polygons": 129,
            "target_img_size": 119571,
            "generated_img_size": 101133
        },
        {
            "algorithm": "sa",
            "fitness": 99.5598,
            "polygons": 50,
            "target_img_size": 119571,
            "generated_img_size": 62881
        }
    ],
    "caragiale1": [
        {
            "algorithm": "ga",
            "fitness": 96.7804,
            "polygons": 290,
            "target_img_size": 34111,
            "generated_img_size": 183497
        },
        {
            "algorithm": "hcfi",
            "fitness": 97.6199,
            "polygons": 99,
            "target_img_size": 34111,
            "generated_img_size": 91772
        },
        {
            "algorithm": "hcbi",
            "fitness": 97.3498,
            "polygons": 106,
            "target_img_size": 34111,
            "generated_img_size": 91538
        },
        {
            "algorithm": "sa",
            "fitness": 97.5746,
            "polygons": 144,
            "target_img_size": 34111,
            "generated_img_size": 112540
        }
    ],
    "cat": [
        {
            "algorithm": "ga",
            "fitness": 99.0677,
            "polygons": 265,
            "target_img_size": 2395352,
            "generated_img_size": 167992
        },
        {
            "algorithm": "hcfi",
            "fitness": 99.299,
            "polygons": 110,
            "target_img_size": 2395352,
            "generated_img_size": 95244
        },
        {
            "algorithm": "hcbi",
            "fitness": 99.2804,
            "polygons": 111,
            "target_img_size": 2395352,
            "generated_img_size": 94104
        },
        {
            "algorithm": "sa",
            "fitness": 99.2858,
            "polygons": 92,
            "target_img_size": 2395352,
            "generated_img_size": 84048
        }
    ],
    "croissant": [
        {
            "algorithm": "ga",
            "fitness": 98.8961,
            "polygons": 294,
            "target_img_size": 376151,
            "generated_img_size": 176791
        },
        {
            "algorithm": "hcfi",
            "fitness": 99.30499999999999,
            "polygons": 106,
            "target_img_size": 376151,
            "generated_img_size": 93163
        },
        {
            "algorithm": "hcbi",
            "fitness": 99.19200000000001,
            "polygons": 122,
            "target_img_size": 376151,
            "generated_img_size": 97195
        },
        {
            "algorithm": "sa",
            "fitness": 99.31060000000001,
            "polygons": 79,
            "target_img_size": 376151,
            "generated_img_size": 78033
        }
    ],
    "eagle": [
        {
            "algorithm": "ga",
            "fitness": 98.91489999999999,
            "polygons": 300,
            "target_img_size": 194276,
            "generated_img_size": 182992
        },
        {
            "algorithm": "hcfi",
            "fitness": 99.2464,
            "polygons": 92,
            "target_img_size": 194276,
            "generated_img_size": 87143
        },
        {
            "algorithm": "hcbi",
            "fitness": 99.2154,
            "polygons": 116,
            "target_img_size": 194276,
            "generated_img_size": 97785
        },
        {
            "algorithm": "sa",
            "fitness": 99.2074,
            "polygons": 110,
            "target_img_size": 194276,
            "generated_img_size": 93769
        }
    ],
    "eminescu": [
        {
            "algorithm": "ga",
            "fitness": 98.6471,
            "polygons": 291,
            "target_img_size": 266626,
            "generated_img_size": 174260
        },
        {
            "algorithm": "hcfi",
            "fitness": 99.13340000000001,
            "polygons": 112,
            "target_img_size": 266626,
            "generated_img_size": 99929
        },
        {
            "algorithm": "hcbi",
            "fitness": 99.0983,
            "polygons": 113,
            "target_img_size": 266626,
            "generated_img_size": 96956
        },
        {
            "algorithm": "sa",
            "fitness": 99.2318,
            "polygons": 86,
            "target_img_size": 266626,
            "generated_img_size": 82997
        }
    ],
    "fractal": [
        {
            "algorithm": "ga",
            "fitness": 94.99210000000001,
            "polygons": 295,
            "target_img_size": 258081,
            "generated_img_size": 182800
        },
        {
            "algorithm": "hcfi",
            "fitness": 96.6387,
            "polygons": 65,
            "target_img_size": 258081,
            "generated_img_size": 73559
        },
        {
            "algorithm": "hcbi",
            "fitness": 96.5507,
            "polygons": 63,
            "target_img_size": 258081,
            "generated_img_size": 70063
        },
        {
            "algorithm": "sa",
            "fitness": 96.7368,
            "polygons": 50,
            "target_img_size": 258081,
            "generated_img_size": 64130
        }
    ],
    "ginevra": [
        {
            "algorithm": "ga",
            "fitness": 99.002,
            "polygons": 288,
            "target_img_size": 183569,
            "generated_img_size": 179566
        },
        {
            "algorithm": "hcfi",
            "fitness": 99.4232,
            "polygons": 93,
            "target_img_size": 183569,
            "generated_img_size": 86211
        },
        {
            "algorithm": "hcbi",
            "fitness": 99.4112,
            "polygons": 84,
            "target_img_size": 183569,
            "generated_img_size": 76830
        },
        {
            "algorithm": "sa",
            "fitness": 99.37989999999999,
            "polygons": 136,
            "target_img_size": 183569,
            "generated_img_size": 109790
        }
    ],
    "girl": [
        {
            "algorithm": "ga",
            "fitness": 99.4268,
            "polygons": 60,
            "target_img_size": 215583,
            "generated_img_size": 64075
        },
        {
            "algorithm": "hcfi",
            "fitness": 99.62140000000001,
            "polygons": 141,
            "target_img_size": 215583,
            "generated_img_size": 110001
        },
        {
            "algorithm": "hcbi",
            "fitness": 99.62450000000001,
            "polygons": 88,
            "target_img_size": 215583,
            "generated_img_size": 81541
        },
        {
            "algorithm": "sa",
            "fitness": 99.6546,
            "polygons": 150,
            "target_img_size": 215583,
            "generated_img_size": 114242
        }
    ],
    "house": [
        {
            "algorithm": "ga",
            "fitness": 97.8769,
            "polygons": 257,
            "target_img_size": 290929,
            "generated_img_size": 164490
        },
        {
            "algorithm": "hcfi",
            "fitness": 98.1997,
            "polygons": 100,
            "target_img_size": 290929,
            "generated_img_size": 89907
        },
        {
            "algorithm": "hcbi",
            "fitness": 98.17660000000001,
            "polygons": 110,
            "target_img_size": 290929,
            "generated_img_size": 94204
        },
        {
            "algorithm": "sa",
            "fitness": 98.20020000000001,
            "polygons": 52,
            "target_img_size": 290929,
            "generated_img_size": 64533
        }
    ],
    "iron": [
        {
            "algorithm": "ga",
            "fitness": 99.5919,
            "polygons": 50,
            "target_img_size": 30029,
            "generated_img_size": 57712
        },
        {
            "algorithm": "hcfi",
            "fitness": 99.687,
            "polygons": 104,
            "target_img_size": 30029,
            "generated_img_size": 90103
        },
        {
            "algorithm": "hcbi",
            "fitness": 99.6656,
            "polygons": 112,
            "target_img_size": 30029,
            "generated_img_size": 88607
        },
        {
            "algorithm": "sa",
            "fitness": 99.6968,
            "polygons": 56,
            "target_img_size": 30029,
            "generated_img_size": 65263
        }
    ],
    "lady": [
        {
            "algorithm": "ga",
            "fitness": 99.7001,
            "polygons": 58,
            "target_img_size": 76883,
            "generated_img_size": 65967
        },
        {
            "algorithm": "hcfi",
            "fitness": 99.76660000000001,
            "polygons": 92,
            "target_img_size": 76883,
            "generated_img_size": 83213
        },
        {
            "algorithm": "hcbi",
            "fitness": 99.7603,
            "polygons": 103,
            "target_img_size": 76883,
            "generated_img_size": 87234
        },
        {
            "algorithm": "sa",
            "fitness": 99.79289999999999,
            "polygons": 109,
            "target_img_size": 76883,
            "generated_img_size": 94429
        }
    ],
    "lincoln": [
        {
            "algorithm": "ga",
            "fitness": 99.1442,
            "polygons": 267,
            "target_img_size": 535627,
            "generated_img_size": 163740
        },
        {
            "algorithm": "hcfi",
            "fitness": 99.5084,
            "polygons": 125,
            "target_img_size": 535627,
            "generated_img_size": 104623
        },
        {
            "algorithm": "hcbi",
            "fitness": 99.4306,
            "polygons": 111,
            "target_img_size": 535627,
            "generated_img_size": 91130
        },
        {
            "algorithm": "sa",
            "fitness": 99.5627,
            "polygons": 139,
            "target_img_size": 535627,
            "generated_img_size": 110791
        }
    ],
    "logoFii": [
        {
            "algorithm": "ga",
            "fitness": 99.8035,
            "polygons": 292,
            "target_img_size": 11316,
            "generated_img_size": 180319
        },
        {
            "algorithm": "hcfi",
            "fitness": 99.8844,
            "polygons": 58,
            "target_img_size": 11316,
            "generated_img_size": 68150
        },
        {
            "algorithm": "hcbi",
            "fitness": 99.8739,
            "polygons": 57,
            "target_img_size": 11316,
            "generated_img_size": 67176
        },
        {
            "algorithm": "sa",
            "fitness": 99.8802,
            "polygons": 54,
            "target_img_size": 11316,
            "generated_img_size": 65974
        }
    ],
    "marilyn": [
        {
            "algorithm": "ga",
            "fitness": 98.4553,
            "polygons": 272,
            "target_img_size": 89306,
            "generated_img_size": 169717
        },
        {
            "algorithm": "hcfi",
            "fitness": 98.9689,
            "polygons": 129,
            "target_img_size": 89306,
            "generated_img_size": 104336
        },
        {
            "algorithm": "hcbi",
            "fitness": 98.925,
            "polygons": 120,
            "target_img_size": 89306,
            "generated_img_size": 101986
        },
        {
            "algorithm": "sa",
            "fitness": 99.0044,
            "polygons": 115,
            "target_img_size": 89306,
            "generated_img_size": 97753
        }
    ],
    "mona": [
        {
            "algorithm": "ga",
            "fitness": 99.1841,
            "polygons": 51,
            "target_img_size": 68157,
            "generated_img_size": 59386
        },
        {
            "algorithm": "hcfi",
            "fitness": 99.3154,
            "polygons": 84,
            "target_img_size": 68157,
            "generated_img_size": 80865
        },
        {
            "algorithm": "hcbi",
            "fitness": 99.2773,
            "polygons": 126,
            "target_img_size": 68157,
            "generated_img_size": 102133
        },
        {
            "algorithm": "sa",
            "fitness": 99.3277,
            "polygons": 86,
            "target_img_size": 68157,
            "generated_img_size": 84763
        }
    ],
    "musashi": [
        {
            "algorithm": "ga",
            "fitness": 98.985,
            "polygons": 300,
            "target_img_size": 203039,
            "generated_img_size": 188852
        },
        {
            "algorithm": "hcfi",
            "fitness": 99.1836,
            "polygons": 106,
            "target_img_size": 203039,
            "generated_img_size": 92703
        },
        {
            "algorithm": "hcbi",
            "fitness": 99.1887,
            "polygons": 109,
            "target_img_size": 203039,
            "generated_img_size": 94544
        },
        {
            "algorithm": "sa",
            "fitness": 99.2081,
            "polygons": 155,
            "target_img_size": 203039,
            "generated_img_size": 115922
        }
    ],
    "mushroom": [
        {
            "algorithm": "ga",
            "fitness": 97.6876,
            "polygons": 135,
            "target_img_size": 464651,
            "generated_img_size": 105645
        },
        {
            "algorithm": "hcfi",
            "fitness": 97.86449999999999,
            "polygons": 135,
            "target_img_size": 464651,
            "generated_img_size": 106818
        },
        {
            "algorithm": "hcbi",
            "fitness": 97.91499999999999,
            "polygons": 139,
            "target_img_size": 464651,
            "generated_img_size": 108392
        },
        {
            "algorithm": "sa",
            "fitness": 98.00569999999999,
            "polygons": 57,
            "target_img_size": 464651,
            "generated_img_size": 66687
        }
    ],
    "peisaj2": [
        {
            "algorithm": "ga",
            "fitness": 99.2444,
            "polygons": 274,
            "target_img_size": 56507,
            "generated_img_size": 171192
        },
        {
            "algorithm": "hcfi",
            "fitness": 99.4432,
            "polygons": 101,
            "target_img_size": 56507,
            "generated_img_size": 87859
        },
        {
            "algorithm": "hcbi",
            "fitness": 99.4404,
            "polygons": 113,
            "target_img_size": 56507,
            "generated_img_size": 96027
        },
        {
            "algorithm": "sa",
            "fitness": 99.4478,
            "polygons": 155,
            "target_img_size": 56507,
            "generated_img_size": 118538
        }
    ],
    "peisaj": [
        {
            "algorithm": "ga",
            "fitness": 99.1061,
            "polygons": 270,
            "target_img_size": 1807227,
            "generated_img_size": 170365
        },
        {
            "algorithm": "hcfi",
            "fitness": 99.2949,
            "polygons": 93,
            "target_img_size": 1807227,
            "generated_img_size": 85466
        },
        {
            "algorithm": "hcbi",
            "fitness": 99.29289999999999,
            "polygons": 92,
            "target_img_size": 1807227,
            "generated_img_size": 82915
        },
        {
            "algorithm": "sa",
            "fitness": 99.3375,
            "polygons": 109,
            "target_img_size": 1807227,
            "generated_img_size": 93793
        }
    ],
    "rubicks": [
        {
            "algorithm": "ga",
            "fitness": 96.16510000000001,
            "polygons": 295,
            "target_img_size": 805248,
            "generated_img_size": 182636
        },
        {
            "algorithm": "hcfi",
            "fitness": 98.3104,
            "polygons": 95,
            "target_img_size": 805248,
            "generated_img_size": 87179
        },
        {
            "algorithm": "hcbi",
            "fitness": 98.2955,
            "polygons": 101,
            "target_img_size": 805248,
            "generated_img_size": 90348
        },
        {
            "algorithm": "sa",
            "fitness": 98.2291,
            "polygons": 132,
            "target_img_size": 805248,
            "generated_img_size": 105982
        }
    ],
    "scream": [
        {
            "algorithm": "ga",
            "fitness": 98.9364,
            "polygons": 269,
            "target_img_size": 57415,
            "generated_img_size": 171837
        },
        {
            "algorithm": "hcfi",
            "fitness": 99.21799999999999,
            "polygons": 112,
            "target_img_size": 57415,
            "generated_img_size": 96416
        },
        {
            "algorithm": "hcbi",
            "fitness": 99.1799,
            "polygons": 113,
            "target_img_size": 57415,
            "generated_img_size": 95012
        },
        {
            "algorithm": "sa",
            "fitness": 99.20060000000001,
            "polygons": 67,
            "target_img_size": 57415,
            "generated_img_size": 74084
        }
    ],
    "space": [
        {
            "algorithm": "ga",
            "fitness": 98.9383,
            "polygons": 67,
            "target_img_size": 1384318,
            "generated_img_size": 66191
        },
        {
            "algorithm": "hcfi",
            "fitness": 99.185,
            "polygons": 113,
            "target_img_size": 1384318,
            "generated_img_size": 94579
        },
        {
            "algorithm": "hcbi",
            "fitness": 99.1696,
            "polygons": 113,
            "target_img_size": 1384318,
            "generated_img_size": 94062
        },
        {
            "algorithm": "sa",
            "fitness": 99.21560000000001,
            "polygons": 59,
            "target_img_size": 1384318,
            "generated_img_size": 68996
        }
    ],
    "starry": [
        {
            "algorithm": "ga",
            "fitness": 98.5813,
            "polygons": 253,
            "target_img_size": 761436,
            "generated_img_size": 154166
        },
        {
            "algorithm": "hcfi",
            "fitness": 98.8089,
            "polygons": 124,
            "target_img_size": 761436,
            "generated_img_size": 102370
        },
        {
            "algorithm": "hcbi",
            "fitness": 98.8128,
            "polygons": 137,
            "target_img_size": 761436,
            "generated_img_size": 106335
        },
        {
            "algorithm": "sa",
            "fitness": 98.8015,
            "polygons": 50,
            "target_img_size": 761436,
            "generated_img_size": 63509
        }
    ],
    "tower": [
        {
            "algorithm": "ga",
            "fitness": 98.4182,
            "polygons": 112,
            "target_img_size": 119273,
            "generated_img_size": 91659
        },
        {
            "algorithm": "hcfi",
            "fitness": 98.75150000000001,
            "polygons": 115,
            "target_img_size": 119273,
            "generated_img_size": 98428
        },
        {
            "algorithm": "hcbi",
            "fitness": 98.73140000000001,
            "polygons": 124,
            "target_img_size": 119273,
            "generated_img_size": 97027
        },
        {
            "algorithm": "sa",
            "fitness": 98.7529,
            "polygons": 79,
            "target_img_size": 119273,
            "generated_img_size": 79873
        }
    ],
    "van": [
        {
            "algorithm": "ga",
            "fitness": 98.3823,
            "polygons": 271,
            "target_img_size": 41464,
            "generated_img_size": 169309
        },
        {
            "algorithm": "hcfi",
            "fitness": 98.7476,
            "polygons": 99,
            "target_img_size": 41464,
            "generated_img_size": 88764
        },
        {
            "algorithm": "hcbi",
            "fitness": 98.7644,
            "polygons": 123,
            "target_img_size": 41464,
            "generated_img_size": 101246
        },
        {
            "algorithm": "sa",
            "fitness": 98.8523,
            "polygons": 109,
            "target_img_size": 41464,
            "generated_img_size": 97293
        }
    ],
    "ww": [
        {
            "algorithm": "ga",
            "fitness": 99.64,
            "polygons": 52,
            "target_img_size": 68540,
            "generated_img_size": 63460
        },
        {
            "algorithm": "hcfi",
            "fitness": 99.7204,
            "polygons": 73,
            "target_img_size": 68540,
            "generated_img_size": 75753
        },
        {
            "algorithm": "hcbi",
            "fitness": 99.7252,
            "polygons": 95,
            "target_img_size": 68540,
            "generated_img_size": 83951
        },
        {
            "algorithm": "sa",
            "fitness": 99.7478,
            "polygons": 84,
            "target_img_size": 68540,
            "generated_img_size": 78669
        }
    ],
    "zebra": [
        {
            "algorithm": "ga",
            "fitness": 96.3278,
            "polygons": 286,
            "target_img_size": 417578,
            "generated_img_size": 177925
        },
        {
            "algorithm": "hcfi",
            "fitness": 96.9971,
            "polygons": 81,
            "target_img_size": 417578,
            "generated_img_size": 81596
        },
        {
            "algorithm": "hcbi",
            "fitness": 96.988,
            "polygons": 77,
            "target_img_size": 417578,
            "generated_img_size": 78607
        },
        {
            "algorithm": "sa",
            "fitness": 97.20020000000001,
            "polygons": 126,
            "target_img_size": 417578,
            "generated_img_size": 103537
        }
    ]
}